lagran/__init__.py
lagran/asgi.py
lagran/settings.py
lagran/urls.py
lagran/wsgi.py
lagran_admin/__init__.py
lagran_admin/admin.py
lagran_admin/apps.py
lagran_admin/models.py
lagran_admin/tests.py
lagran_admin/views.py
lagran_admin/migrations/__init__.py
lagran_admin/static/admin/css/autocomplete.css
lagran_admin/static/admin/css/base.css
lagran_admin/static/admin/css/changelists.css
lagran_admin/static/admin/css/custom.css
lagran_admin/static/admin/css/dark_mode.css
lagran_admin/static/admin/css/dashboard.css
lagran_admin/static/admin/css/forms.css
lagran_admin/static/admin/css/login.css
lagran_admin/static/admin/css/nav_sidebar.css
lagran_admin/static/admin/css/responsive.css
lagran_admin/static/admin/css/responsive_rtl.css
lagran_admin/static/admin/css/rtl.css
lagran_admin/static/admin/css/widgets.css
lagran_admin/static/admin/css/vendor/select2/LICENSE-SELECT2.md
lagran_admin/static/admin/css/vendor/select2/select2.css
lagran_admin/static/admin/css/vendor/select2/select2.min.css
lagran_admin/static/admin/img/LICENSE
lagran_admin/static/admin/img/README.txt
lagran_admin/static/admin/img/calendar-icons.svg
lagran_admin/static/admin/img/icon-addlink.svg
lagran_admin/static/admin/img/icon-alert.svg
lagran_admin/static/admin/img/icon-calendar.svg
lagran_admin/static/admin/img/icon-changelink.svg
lagran_admin/static/admin/img/icon-clock.svg
lagran_admin/static/admin/img/icon-deletelink.svg
lagran_admin/static/admin/img/icon-no.svg
lagran_admin/static/admin/img/icon-unknown-alt.svg
lagran_admin/static/admin/img/icon-unknown.svg
lagran_admin/static/admin/img/icon-viewlink.svg
lagran_admin/static/admin/img/icon-yes.svg
lagran_admin/static/admin/img/inline-delete.svg
lagran_admin/static/admin/img/lagran.png
lagran_admin/static/admin/img/lagran1.png
lagran_admin/static/admin/img/search.svg
lagran_admin/static/admin/img/selector-icons.svg
lagran_admin/static/admin/img/sorting-icons.svg
lagran_admin/static/admin/img/tooltag-add.svg
lagran_admin-0.4.dist-info/LICENSE
lagran_admin-0.4.dist-info/METADATA
lagran_admin-0.4.dist-info/WHEEL
lagran_admin-0.4.dist-info/top_level.txt
lagran_admin-0.4.dist-info/RECORD
